curricula_compile/__init__.py
curricula_compile/compilation.py
curricula_compile/content.py
curricula_compile/exception.py
curricula_compile/framework.py
curricula_compile/models.py
curricula_compile/shell.py
curricula_compile/validate.py
curricula_compile/version.py
curricula_compile/schema/assignment.schema.json
curricula_compile/schema/assignment_grading.schema.json
curricula_compile/schema/assignment_meta.schema.json
curricula_compile/schema/author.schema.json
curricula_compile/schema/datetime.schema.json
curricula_compile/schema/problem.schema.json
curricula_compile/schema/problem_grading.schema.json
curricula_compile/schema/problem_grading_category.schema.json
curricula_compile/schema/problem_reference.schema.json
curricula_compile/schema/problem_reference_grading.schema.json
curricula_compile/schema/problem_reference_grading_category.schema.json
curricula_compile/template/grading/assignment.md
curricula_compile/template/grading/problem.md
curricula_compile/template/instructions/assignment.md
curricula_compile/template/instructions/problem.md
curricula_compile/template/solution/assignment.md
curricula_compile/template/solution/problem.md
curricula_compile/tools/__init__.py
curricula_compile/tools/generate.py
curricula_compile/workflows/__init__.py
curricula_compile/workflows/grade.py
curricula_compile/workflows/site.py
curricula_compile-2.1.0.dist-info/LICENSE
curricula_compile-2.1.0.dist-info/METADATA
curricula_compile-2.1.0.dist-info/WHEEL
curricula_compile-2.1.0.dist-info/top_level.txt
curricula_compile-2.1.0.dist-info/RECORD
