Metadata-Version: 2.1
Name: curricula-compile
Version: 2.1.0
Summary: An assignment bundler for the Curricula ecosystem
Home-page: https://github.com/curriculagg/curricula
Author: Noah Kim
Author-email: noahbkim@gmail.com
License: UNKNOWN
Platform: UNKNOWN
Requires-Python: >=3.9
Requires-Dist: jinja2
Requires-Dist: jsonschema
Requires-Dist: watchdog
Requires-Dist: curricula (~=2.1.0)
